pyznap/__init__.py
pyznap/clean.py
pyznap/main.py
pyznap/process.py
pyznap/pyzfs.py
pyznap/send.py
pyznap/ssh.py
pyznap/take.py
pyznap/utils.py
pyznap/config/pyznap.conf
pyznap-1.6.0.dist-info/LICENSE
pyznap-1.6.0.dist-info/METADATA
pyznap-1.6.0.dist-info/WHEEL
pyznap-1.6.0.dist-info/entry_points.txt
pyznap-1.6.0.dist-info/top_level.txt
pyznap-1.6.0.dist-info/RECORD
