Metadata-Version: 2.1
Name: pyznap
Version: 1.6.0
Summary: ZFS snapshot tool written in Python
Home-page: https://github.com/yboetz/pyznap
Author: Yannick Boetzel
Author-email: github@boetzel.ch
License: GPLv3
Keywords: zfs snapshot backup
Platform: UNKNOWN
Classifier: Development Status :: 5 - Production/Stable
Classifier: Environment :: Console
Classifier: Intended Audience :: End Users/Desktop
Classifier: License :: OSI Approved :: GNU General Public License v3 (GPLv3)
Classifier: Operating System :: Unix
Classifier: Programming Language :: Python
Classifier: Programming Language :: Python :: 3
Classifier: Programming Language :: Python :: 3.5
Classifier: Programming Language :: Python :: 3.6
Classifier: Programming Language :: Python :: 3.7
Classifier: Topic :: System :: Archiving :: Backup
Classifier: Topic :: System :: Filesystems
Requires-Python: >=3.5
Provides-Extra: dev
Requires-Dist: pytest ; extra == 'dev'
Requires-Dist: pytest-dependency ; extra == 'dev'
Requires-Dist: pytest-runner ; extra == 'dev'
Requires-Dist: paramiko (>=2.4.2) ; extra == 'dev'
